woapylint/__init__.py
woapylint/assert_message_checker.py
woapylint/forbidden_class_checker.py
woapylint/forbidden_string_checker.py
woapylint/invoke_method_checker.py
woapylint/long_string_checker.py
woapylint/string_whitespace_checker.py
woapylint-0.1.0.dist-info/METADATA
woapylint-0.1.0.dist-info/WHEEL
woapylint-0.1.0.dist-info/RECORD
