Metadata-Version: 2.3
Name: woapylint
Version: 0.1.0
Summary: woapylint
Author: manhdt
Author-email: thitkhotau.no1@gmail.com
Requires-Python: >=3.12
Classifier: Programming Language :: Python :: 3
Classifier: Programming Language :: Python :: 3.12
Classifier: Programming Language :: Python :: 3.13
Requires-Dist: pylint (>=3.3.6,<4.0.0)
